[
    {
        "id": 0,
        "session": "SPA e Fragrâncias",
        "line": "Perfumes",
        "image": "10-051954.jpg",
        "points": 50,
        "title": "Black Diamonds Desodorante Colônia - 60 ml",
        "price": 84,
        "status": "Lançamento",
        "extra": "mais vendido",
        "description": "Uma fragrância floral, perfeita para mulheres intensas e marcantes.",
        "gridList": [
            {
                "SKU": "10-051954"
            }
        ]
    },
    {
        "id": 1,
        "session": "SPA e Fragrâncias",
        "line": "Perfumes",
        "image": "10-060686.jpg",
        "points": 57,
        "title": "Upscale Eau de Parfum - 75 ml",
        "price": 99,
        "status": "Lançamento",
        "description": "Perfeita para o homem sofisticado, seguro e de personalidade forte.",
        "gridList": [
            {
                "SKU": "10-060686"
            }
        ]
    },
    {
        "id": 2,
        "session": "Maquiagem",
        "line": "Maquiagem",
        "image": "10-058473.jpg",
        "points": 29,
        "title": "Primer Facial Fixador de Maquiagem com FPS 15 - 29 ml",
        "price": 56,
        "status": "Lançamento",
        "description": "Melhora o aspecto da pele, realçando os benefícios da base e amenizando imperfeições.",
        "gridList": [
            {
                "SKU": "10-058473"
            }
        ]
    },
    {
        "id": 3,
        "session": "Maquiagem",
        "line": "Maquiagem",
        "image": "10-058264.png",
        "points": 25,
        "title": "Máscara Alongadora para Cílios Lash Love à Prova D'Água - 8 g",
        "price": 51,
        "status": "Lançamento",
        "description": "Todos os benefícios da Máscara Alongadora Lash Love com a resistência à água.",
        "gridList": [
            {
                "SKU": "10-058264",
                "option": "Preta"
            }
        ]
    },
    {
        "id": 4,
        "session": "Maquiagem",
        "line": "Maquiagem",
        "image": "10-059505.jpg",
        "points": 27,
        "title": "Base Líquida TimeWise - Acabamento Matte - 29 ml ",
        "price": 54,
        "status": "Lançamento",
        "description": "Fórmula leve, que ajuda a controlar o excesso de oleosidade e o brilho durante todo o dia. Diminui a aparência de rugas e linhas finas.",
        "gridList": [
            {
                "SKU": "10-059517",
                "option": "Beige 7"
            },
            {
                "SKU": "10-059518",
                "option": "Beige 8"
            },
            {
                "SKU": "10-059505",
                "option": "Ivory 3"
            }
        ]
    },
    {
        "id": 5,
        "session": "Maquiagem",
        "line": "Maquiagem",
        "image": "10-059976.jpg",
        "points": 27,
        "title": "Base Líquida TimeWise - Acabamento Luminoso - 29 ml",
        "price": 54,
        "status": "Lançamento",
        "description": "Proporciona uma pele com luminosidade e visual radiante com a melhora do aspecto da textura da pele.",
        "gridList": [
            {
                "SKU": "10-059533",
                "option": "Beige 7"
            },
            {
                "SKU": "10-059534",
                "option": "Beige 8"
            },
            {
                "SKU": "10-059976",
                "option": "Ivory 3"
            }
        ]
    },
    {
        "id": 6,
        "session": "Maquiagem",
        "line": "Zen in Bloom",
        "image": "10-060636.jpg",
        "points": 24,
        "title": "Trio de Sombras - 10 g",
        "price": 48,
        "status": "Ed. Limitada",
        "description": "Tons pastel com ótima pigmentação. Com sistema refil, fica perfeito no Mini Estojo Compacto da Mary Kay. ",
        "gridList": [
            {
                "SKU": "10-060636",
                "option": "Garden Sky"
            }
        ]
    },
    {
        "id": 7,
        "session": "Maquiagem",
        "line": "Zen in Bloom",
        "image": "10-060585.png",
        "points": 11,
        "title": "Esmalte para as Unhas - 4 g",
        "price": 22,
        "status": "Ed. Limitada",
        "description": "Acabamento brilhante com coloração intensa. Fórmula especial, que permite cor uniforme e longa duração. Os tons foram inspirados nos jardins orientais.",
        "gridList": [
            {
                "SKU": "10-060584",
                "option": "Blue Lotus"
            },
            {
                "SKU": "10-060583",
                "option": "Pink Bamboo"
            },
            {
                "SKU": "10-060585",
                "option": "Ginseng Blossom"
            }
        ]
    },
    {
        "id": 8,
        "session": "Maquiagem",
        "line": "Zen in Bloom",
        "image": "10-061345.jpg",
        "points": 23,
        "title": "Brilho Labial - 4 g",
        "price": 45,
        "status": "Ed. Limitada",
        "description": "Cores intensas com fórmula hidratante e suave.",
        "gridList": [
            {
                "SKU": "10-061344",
                "option": "Pink Pagoda"
            },
            {
                "SKU": "10-061345",
                "option": "Chai Latte"
            }
        ]
    },
    {
        "id": 9,
        "session": "Maquiagem",
        "line": "Maquiagem",
        "image": "10-025874.jpg",
        "points": 20,
        "title": "Sombra em Creme - 4,3 g",
        "price": 35,
        "status": "Ed. Limitada",
        "description": "De fácil aplicação, você pode usá-las sozinhas ou como primer antes das sombras minerais.",
        "gridList": [
            {
                "SKU": "10-025868",
                "option": "Beach Blonde"
            },
            {
                "SKU": "10-025876",
                "option": "Glacier Gray"
            },
            {
                "SKU": "10-025875",
                "option": "Pale Blush"
            },
            {
                "SKU": "10-025874",
                "option": "Apricot Twist"
            }
        ]
    },
    {
        "id": 10,
        "session": "Maquiagem",
        "line": "Hollywood Mystique",
        "image": "10-056218.jpg",
        "points": 21,
        "title": "Batom Líquido Ultra Brilho - 3g",
        "price": 38,
        "status": "Ed. Limitada",
        "description": "Cobertura intensa e acabamento com brilho.",
        "gridList": [
            {
                "SKU": "10-056219",
                "option": "Bold Fuchsia"
            },
            {
                "SKU": "10-056220",
                "option": "Poised Pink"
            },
            {
                "SKU": "10-056218",
                "option": "Radiant Red"
            }
        ]
    },
    {
        "id": 11,
        "session": "Maquiagem",
        "line": "Hollywood Mystique",
        "image": "10-056222.jpg",
        "points": 26,
        "title": "Delineador em Gel - 4,5 g",
        "price": 47,
        "status": "Ed. Limitada",
        "gridList": [
            {
                "SKU": "10-056222",
                "option": "Tempting Teal"
            }
        ]
    },
    {
        "id": 12,
        "session": "Maquiagem",
        "line": "Acessórios",
        "image": "10-067480.jpg",
        "points": 33,
        "title": "Mini Coleção de Pincéis Glam",
        "price": 65,
        "status": "Ed. Limitada",
        "description": "São quatro mini pincéis em uma linda nècessaire. Ideal para levar na bolsa e reaplicar a maquiagem a qualquer hora.",
        "gridList": [
            {
                "SKU": "10-067480"
            }
        ]
    },
    {
        "id": 13,
        "session": "Maquiagem",
        "line": "Acessórios",
        "image": "10-054125.jpg",
        "points": 33,
        "title": "Mini Estojo Compacto - Edição Especial de Aniversário (vazio)",
        "price": 52,
        "status": "Ed. Limitada",
        "description": "Ele vem com um cristal Swarovski dourado, simbolizando o quanto as ações de uma pessoa podem transformar o mundo.",
        "gridList": [
            {
                "SKU": "10-054125"
            }
        ]
    },
    {
        "id": 14,
        "session": "SPA e Fragrâncias",
        "line": "Perfumes",
        "image": "10-055778.jpg",
        "points": 75,
        "title": "Dance To Life Eau de Parfum - 50 ml",
        "price": 149,
        "status": "Ed. Limitada",
        "description": "Uma fragrância floral desenvolvida especialmente para comemorar os 50 anos da Mary Kay.",
        "gridList": [
            {
                "SKU": "10-055778"
            }
        ]
    },
    {
        "id": 15,
        "session": "Cuidados com a Pele",
        "line": "TimeWise",
        "image": "10-042751.jpg",
        "points": 37,
        "title": "Creme de Limpeza 3 em 1 - 127 g",
        "price": 58,
        "status": "Linha Regular",
        "description": "Limpa, esfolia e tonifica em apenas um passo. Escolha entre as opções mista a oleosa ou normal a seca.",
        "gridList": [
            {
                "SKU": "10-042761",
                "option": "Pele Mista/Oleosa"
            },
            {
                "SKU": "10-042751",
                "option": "Pele Normal/Seca"
            }
        ]
    },
    {
        "id": 16,
        "session": "Cuidados com a Pele",
        "line": "TimeWise",
        "image": "10-027914.jpg",
        "points": 37,
        "title": "Sabonete 3 em 1 de Limpeza Facial - 141 g",
        "price": 56,
        "status": "Linha Regular",
        "description": "Sabonete em barra que limpa, esfolia e tonifica. Para pele normal a oleosa.",
        "gridList": [
            {
                "SKU": "10-027914"
            }
        ]
    },
    {
        "id": 17,
        "session": "Cuidados com a Pele",
        "line": "TimeWise",
        "image": "10-042747.jpg",
        "points": 39,
        "title": "Hidratante Redutor de Linhas de Expressão - 88 ml",
        "price": 62,
        "status": "Linha Regular",
        "description": "Hidrata por até dez horas e acelera o processo natural de renovação da pele. Escolha entre as opções mista a oleosa ou normal a seca.",
        "gridList": [
            {
                "SKU": "10-042743",
                "option": "Pele Mista/Oleosa"
            },
            {
                "SKU": "10-042747",
                "option": "Pele Normal/Seca"
            }
        ]
    },
    {
        "id": 18,
        "session": "Cuidados com a Pele",
        "line": "TimeWise",
        "image": "10-042814.jpg",
        "points": 39,
        "title": "Hidratante Redutor de Linhas de Expressão com FPS 15 - 88 ml",
        "price": 65,
        "status": "Linha Regular",
        "description": "Os benefícios do Hidratante Redutor de Linhas de Expressão TimeWise aliados ao fator de proteção solar. Para todos os tipos de pele.",
        "gridList": [
            {
                "SKU": "10-042814"
            }
        ]
    },
    {
        "id": 19,
        "session": "Cuidados com a Pele",
        "line": "TimeWise",
        "image": "10-563500.jpg",
        "points": 94,
        "title": "Kit Solução Diurna e Noturna",
        "price": 153,
        "status": "Linha Regular",
        "gridList": [
            {
                "SKU": "10-563500"
            }
        ]
    },
    {
        "id": 20,
        "session": "Cuidados com a Pele",
        "line": "TimeWise",
        "image": "10-042754.jpg",
        "points": 47,
        "title": "Solução Diurna com FPS 25 - 29 ml",
        "price": 85,
        "status": "Linha Regular",
        "description": "Bloqueia os raios UVA e UVB enquanto os peptídeos calmantes ajudam a relaxar as linhas de expressão.",
        "gridList": [
            {
                "SKU": "10-042754"
            }
        ]
    },
    {
        "id": 21,
        "session": "Cuidados com a Pele",
        "line": "TimeWise",
        "image": "10-042760.jpg",
        "points": 47,
        "title": "Solução Noturna - 29 ml",
        "price": 85,
        "status": "Linha Regular",
        "description": "Vitaminas, antioxidantes e peptídeos intensificadores de colágeno nutrem, suavizam e firmam a pele.",
        "gridList": [
            {
                "SKU": "10-042760"
            }
        ]
    },
    {
        "id": 22,
        "session": "Cuidados com a Pele",
        "line": "TimeWise",
        "image": "10-026901.jpg",
        "points": 170,
        "title": "Sistema Anti-idade de Cuidados com a Pele",
        "price": 273,
        "status": "Linha Regular",
        "gridList": [
            {
                "SKU": "10-026902",
                "option": "Pele Mista/Oleosa"
            },
            {
                "SKU": "10-026901",
                "option": "Pele Normal/Seca"
            }
        ]
    },
    {
        "id": 23,
        "session": "Cuidados com a Pele",
        "line": "TimeWise",
        "image": "10-054641.jpg",
        "points": 64,
        "title": "Sérum Facial Renovador - 44 ml",
        "price": 110,
        "status": "Linha Regular",
        "description": "Atua na área específica da pele em que está presente o colágeno e a elastina, oferece ação lifting e deixa a pele do rosto com aparência mais firme.",
        "gridList": [
            {
                "SKU": "10-054641"
            }
        ]
    },
    {
        "id": 24,
        "session": "Cuidados com a Pele",
        "line": "TimeWise",
        "image": "10-046752.jpg",
        "points": 47,
        "title": "Complexo Facial Noturno - 50 g",
        "price": 85,
        "status": "Linha Regular",
        "description": "Ajuda a restaurar a pele e ativa a produção de colágeno. Escolha entre as opções mista a oleosa ou normal a seca.",
        "gridList": [
            {
                "SKU": "10-046753",
                "option": "Pele Mista/Oleosa"
            },
            {
                "SKU": "10-046752",
                "option": "Pele Normal/Seca"
            }
        ]
    },
    {
        "id": 25,
        "session": "Cuidados com a Pele",
        "line": "TimeWise",
        "image": "10-004300.jpg",
        "points": 98,
        "title": "Kit Microdermoabrasão",
        "price": 162,
        "status": "Linha Regular",
        "description": "Em apenas dois passos, uma pele lisa e suave, além de reduzir a aparência de linhas finas e poros.",
        "gridList": [
            {
                "SKU": "10-004300"
            }
        ]
    },
    {
        "id": 26,
        "session": "Cuidados com a Pele",
        "line": "TimeWise",
        "image": "10-029733.jpg",
        "points": 51,
        "title": "Microdermoabrasão - Passo 1: Refinar - 70 g",
        "price": 92,
        "status": "Linha Regular",
        "gridList": [
            {
                "SKU": "10-029733"
            }
        ]
    },
    {
        "id": 27,
        "session": "Cuidados com a Pele",
        "line": "TimeWise",
        "image": "10-029735.jpg",
        "points": 47,
        "title": "Microdermoabrasão - Passo 2: Restaurar - 29 ml",
        "price": 88,
        "status": "Linha Regular",
        "gridList": [
            {
                "SKU": "10-029735"
            }
        ]
    },
    {
        "id": 28,
        "session": "Cuidados com a Pele",
        "line": "TimeWise",
        "image": "10-039964.jpg",
        "points": 35,
        "title": "Máscara Hidratante Renovadora em Gel - 85 g",
        "price": 59,
        "status": "Linha Regular",
        "description": "Dez minutos para uma pele incrivelmente hidratada e fresca.",
        "gridList": [
            {
                "SKU": "10-039964"
            }
        ]
    },
    {
        "id": 29,
        "session": "Cuidados com a Pele",
        "line": "TimeWise",
        "image": "10-031174.jpg",
        "points": 37,
        "title": "Máscara Even Complexion - 85 g",
        "price": 67,
        "status": "Linha Regular",
        "description": "Deixa a pele mais radiante, hidratada e com sensação de maciez.",
        "gridList": [
            {
                "SKU": "10-031174"
            }
        ]
    },
    {
        "id": 30,
        "session": "Cuidados com a Pele",
        "line": "TimeWise",
        "image": "10-029730.jpg",
        "points": 55,
        "title": "Loção Even Complexion - 29 ml",
        "price": 96,
        "status": "Linha Regular",
        "description": "Ajuda a pele a ficar com um tom mais uniforme.",
        "gridList": [
            {
                "SKU": "10-029730"
            }
        ]
    },
    {
        "id": 31,
        "session": "Cuidados com a Pele",
        "line": "TimeWise",
        "image": "10-031340.jpg",
        "points": 52,
        "title": "Creme Redutor de Linhas de Expressão Targeted-Action - 6 ml",
        "price": 79,
        "status": "Linha Regular",
        "description": "Firma e preenche linhas e rugas. Perceba resultados em minutos.",
        "gridList": [
            {
                "SKU": "10-031340"
            }
        ]
    },
    {
        "id": 32,
        "session": "Cuidados com a Pele",
        "line": "TimeWise",
        "image": "10-035083.jpg",
        "points": 65,
        "title": "Loção Corporal Firmadora Targeted-Action - 236 ml",
        "price": 97,
        "status": "Linha Regular",
        "description": "Combina vários benefícios em uma só fórmula. Ajuda a deixar a pele firme, tonificada e hidratada por até vinte e quatro horas.",
        "gridList": [
            {
                "SKU": "10-035083"
            }
        ]
    },
    {
        "id": 33,
        "session": "Cuidados com a Pele",
        "line": "TimeWise",
        "image": "10-032946.jpg",
        "points": 35,
        "title": "Creme para Mãos e Colo com FPS 15 - 85 g",
        "price": 65,
        "status": "Linha Regular",
        "description": "Hidrata, minimiza os efeitos nocivos do sol e a aparência de manchas escuras da pele.",
        "gridList": [
            {
                "SKU": "10-032946"
            }
        ]
    },
    {
        "id": 34,
        "session": "Cuidados com a Pele",
        "line": "TimeWise",
        "image": "10-029743.jpg",
        "points": 39,
        "title": "Complexo Anti-idade para os Lábios - 1,6 g",
        "price": 66,
        "status": "Linha Regular",
        "description": "Combate linhas finas e rugas e ainda prolonga a duração do batom.",
        "gridList": [
            {
                "SKU": "10-029743"
            }
        ]
    },
    {
        "id": 35,
        "session": "Cuidados com a Pele",
        "line": "TimeWise",
        "image": "10-042799.jpg",
        "points": 52,
        "title": "Creme Firmador para a Área dos Olhos - 14 g",
        "price": 72,
        "status": "Linha Regular",
        "description": "Firma, ilumina, promove hidratação intensa e minimiza as linhas finas e rugas.",
        "gridList": [
            {
                "SKU": "10-042799"
            }
        ]
    },
    {
        "id": 36,
        "session": "Cuidados com a Pele",
        "line": "TimeWise",
        "image": "10-029728.jpg",
        "points": 52,
        "title": "Creme Anti-idade para Contorno dos Olhos - 18 g",
        "price": 70,
        "status": "Linha Regular",
        "description": "Minimiza a aparência de linhas finas e rugas.",
        "gridList": [
            {
                "SKU": "10-029728"
            }
        ]
    },
    {
        "id": 37,
        "session": "Cuidados com a Pele",
        "line": "TimeWise",
        "image": "10-029737.jpg",
        "points": 52,
        "title": "Revitalizante para a Área dos Olhos Targeted-Action - 10 ml",
        "price": 79,
        "status": "Linha Regular",
        "description": "Reduz olheiras e acaba com o inchaço na região abaixo dos olhos.",
        "gridList": [
            {
                "SKU": "10-029737"
            }
        ]
    },
    {
        "id": 38,
        "session": "Cuidados com a Pele",
        "line": "TimeWise Repair",
        "image": "10-073276.jpg",
        "points": 299,
        "title": "Sistema Volu-Firm",
        "price": 489,
        "status": "Linha Regular",
        "gridList": [
            {
                "SKU": "10-073276"
            }
        ]
    },
    {
        "id": 39,
        "session": "Cuidados com a Pele",
        "line": "TimeWise Repair",
        "image": "10-072912.jpg",
        "points": 114,
        "title": "Kit Creme Diurno e Noturno Volu-Firm",
        "price": 189,
        "status": "Linha Regular",
        "gridList": [
            {
                "SKU": "10-072912"
            }
        ]
    },
    {
        "id": 40,
        "session": "Cuidados com a Pele",
        "line": "TimeWise Repair",
        "image": "10-053074.jpg",
        "points": 42,
        "title": "Espuma de Limpeza Volu-Firm - 127 g",
        "price": 69,
        "status": "Linha Regular",
        "description": "Limpa e renova a textura da pele, minimizando a aparência dos poros.",
        "gridList": [
            {
                "SKU": "10-053074"
            }
        ]
    },
    {
        "id": 41,
        "session": "Cuidados com a Pele",
        "line": "TimeWise Repair",
        "image": "10-048848.jpg",
        "points": 74,
        "title": "Sérum Lifting Volu-Firm - 29 ml",
        "price": 132,
        "status": "Linha Regular",
        "description": "Ajuda a dar firmeza e sustentar a pele. Restaura o volume e firmeza, deixando a sua pele com aparência mais jovem e firme.",
        "gridList": [
            {
                "SKU": "10-048848"
            }
        ]
    },
    {
        "id": 42,
        "session": "Cuidados com a Pele",
        "line": "TimeWise Repair",
        "image": "10-058796.jpg",
        "points": 57,
        "title": "Creme Diurno com FPS 30 Volu-Firm - 48 g",
        "price": 105,
        "status": "Linha Regular",
        "description": "Protege a pele contra futuros danos, hidratando-a e reduzindo a aparência de rugas e linhas de expressão.",
        "gridList": [
            {
                "SKU": "10-058796"
            }
        ]
    },
    {
        "id": 43,
        "session": "Cuidados com a Pele",
        "line": "TimeWise Repair",
        "image": "10-057096.jpg",
        "points": 57,
        "title": "Creme Noturno Volu-Firm - 48 g",
        "price": 105,
        "status": "Linha Regular",
        "description": "Ajuda a recuperar a suavidade da pele, combatendo os sinais avançados da idade. Ajuda a delinear o contorno do rosto, deixando-o mais definido e com menos linhas aparentes.",
        "gridList": [
            {
                "SKU": "10-057096"
            }
        ]
    },
    {
        "id": 44,
        "session": "Cuidados com a Pele",
        "line": "TimeWise Repair",
        "image": "10-047376.jpg",
        "points": 69,
        "title": "Creme para a Área dos Olhos Volu-Firm - 14 g",
        "price": 99,
        "status": "Linha Regular",
        "description": "Muitos benefícios em um produto. Combate linhas profundas, manchas escuras, flacidez, inchaço e pálpebras caídas. A embalagem conta com um exclusivo massageador.",
        "gridList": [
            {
                "SKU": "10-047376"
            }
        ]
    },
    {
        "id": 45,
        "session": "Cuidados com a Pele",
        "line": "Botanical Effects",
        "image": "10-049513.jpg",
        "points": 17,
        "title": "Creme de Limpeza - 113 g",
        "price": 29,
        "status": "Linha Regular",
        "description": "Remove a maquiagem e impurezas, deixando a pele saudável e renovada.",
        "gridList": [
            {
                "SKU": "10-049513",
                "option": "Pele Normal"
            }
        ]
    },
    {
        "id": 46,
        "session": "Cuidados com a Pele",
        "line": "Botanical Effects",
        "image": "10-049516.jpg",
        "points": 17,
        "title": "Gel de Limpeza - 113 g",
        "price": 29,
        "status": "Linha Regular",
        "gridList": [
            {
                "SKU": "10-049516",
                "option": "Pele Oleosa"
            }
        ]
    },
    {
        "id": 47,
        "session": "Cuidados com a Pele",
        "line": "Botanical Effects",
        "image": "10-050141.jpg",
        "points": 28,
        "title": "Máscara Facial - 113 g",
        "price": 49,
        "status": "Linha Regular",
        "description": "Hidrata e limpa os poros, deixando a pele fresca e renovada. Use duas a três vezes por semana.",
        "gridList": [
            {
                "SKU": "10-050144",
                "option": "Pele Oleosa"
            },
            {
                "SKU": "10-050141",
                "option": "Pele Normal"
            }
        ]
    },
    {
        "id": 48,
        "session": "Cuidados com a Pele",
        "line": "Botanical Effects",
        "image": "10-049807.jpg",
        "points": 17,
        "title": "Tônico Refrescante - 147 ml",
        "price": 29,
        "status": "Linha Regular",
        "description": "Remove suavemente os resíduos e proporciona sensação suave e refrescante.",
        "gridList": [
            {
                "SKU": "10-049810",
                "option": "Pele Oleosa"
            },
            {
                "SKU": "10-049807",
                "option": "Pele Normal"
            }
        ]
    },
    {
        "id": 49,
        "session": "Cuidados com a Pele",
        "line": "Botanical Effects",
        "image": "10-049591.jpg",
        "points": 17,
        "title": "Hidratante - 88 ml",
        "price": 29,
        "status": "Linha Regular",
        "description": "Tem absorção rápida e deixa a pele com aparência saudável e equilibrada.",
        "gridList": [
            {
                "SKU": "10-049594",
                "option": "Pele Oleosa"
            },
            {
                "SKU": "10-049591",
                "option": "Pele Normal"
            }
        ]
    },
    {
        "id": 50,
        "session": "Cuidados com a Pele",
        "line": "Acne",
        "image": "10-020374.jpg",
        "points": 34,
        "title": "Gel de Limpeza para Pele com Tendência à Acne - 127 g",
        "price": 50,
        "status": "Linha Regular",
        "description": "Ajuda a remover o excesso de oleosidade e as células mortas, não deixa resíduos na pele. Contém 2% de ácido salicílico.",
        "gridList": [
            {
                "SKU": "10-020374"
            }
        ]
    },
    {
        "id": 51,
        "session": "Cuidados com a Pele",
        "line": "Acne",
        "image": "10-020377.jpg",
        "points": 46,
        "title": "Loção para Pele com Tendência à Acne - 50 g",
        "price": 68,
        "status": "Linha Regular",
        "description": "Formulada com ingredientes botânicos e 2% de ácido salicílico para ajudar a controlar a oleosidade.",
        "gridList": [
            {
                "SKU": "10-020377"
            }
        ]
    },
    {
        "id": 52,
        "session": "Cuidados com a Pele",
        "line": "Acne",
        "image": "10-020379.jpg",
        "points": 31,
        "title": "Creme Secativo para Pele com Tendência à Acne - 29 g",
        "price": 45,
        "status": "Linha Regular",
        "description": "Atua diretamente sobre a acne, ajudando a eliminá-la e prevenindo o surgimento de novos pontos de acne. Contém ingredientes botânicos e 2% de ácido salicílico.",
        "gridList": [
            {
                "SKU": "10-020379"
            }
        ]
    },
    {
        "id": 53,
        "session": "Cuidados com a Pele",
        "line": "Acne",
        "image": "10-029381.jpg",
        "points": 111,
        "title": "Sistema de Cuidados da Pele com Tendência à Acne",
        "price": 163,
        "status": "Linha Regular",
        "description": "Inclui o Gel de Limpeza, a Loção e o Creme Secativo.",
        "gridList": [
            {
                "SKU": "10-029381"
            }
        ]
    },
    {
        "id": 54,
        "session": "Cuidados com a Pele",
        "line": "Acne",
        "image": "10-021628.jpg",
        "points": 65,
        "title": "Kit Introdutório ao Sistema de Cuidados da Pele com Tendência à Acne",
        "price": 95,
        "status": "Linha Regular",
        "description": "Contém os três produtos da linha em tamanho ideal para ser utilizado por um mês.",
        "gridList": [
            {
                "SKU": "10-021628"
            }
        ]
    },
    {
        "id": 55,
        "session": "Cuidados com a Pele",
        "line": "Acne",
        "image": "10-023376.jpg",
        "points": 28,
        "title": "Spray Corporal para Pele com Tendência à Acne - 118 ml",
        "price": 55,
        "status": "Linha Regular",
        "description": "Especialmente desenvolvido com ingredientes botânicos e 2% de ácido salicílico. Para ajudar a combater a acne na pele do corpo. Pode ser aplicado nos ombros, costas e pernas.",
        "gridList": [
            {
                "SKU": "10-023376"
            }
        ]
    },
    {
        "id": 56,
        "session": "Cuidados com a Pele",
        "line": "Clássica",
        "image": "10-105900.jpg",
        "points": 19,
        "title": "Espuma de Limpeza 3 - 192 ml",
        "price": 47,
        "status": "Linha Regular",
        "extra": "compra até 31/12/13",
        "gridList": [
            {
                "SKU": "10-105900"
            }
        ]
    },
    {
        "id": 57,
        "session": "Cuidados com a Pele",
        "line": "Clássica",
        "image": "10-106600.jpg",
        "points": 26,
        "title": "Creme Hidratante Enriquecido 1 - 118 ml",
        "price": 56,
        "status": "Linha Regular",
        "extra": "compra até 31/12/13",
        "gridList": [
            {
                "SKU": "10-106600"
            }
        ]
    },
    {
        "id": 58,
        "session": "Cuidados com a Pele",
        "line": "Clássica",
        "image": "10-106800.jpg",
        "points": 26,
        "title": "Fluido Hidratante para Controle da Oleosidade 3 - 118 ml",
        "price": 56,
        "status": "Linha Regular",
        "extra": "compra até 31/12/13",
        "gridList": [
            {
                "SKU": "10-106800"
            }
        ]
    },
    {
        "id": 59,
        "session": "Cuidados com a Pele",
        "line": "Velocity",
        "image": "10-001600.jpg",
        "points": 24,
        "title": "Gel de Limpeza para o Rosto - 147 ml",
        "price": 43,
        "status": "Linha Regular",
        "extra": "compra até 31/12/13",
        "gridList": [
            {
                "SKU": "10-001600"
            }
        ]
    },
    {
        "id": 60,
        "session": "Cuidados com a Pele",
        "line": "MKMen",
        "image": "10-060198.jpg",
        "points": 25,
        "title": "Creme Intensivo para a Área dos Olhos - 18 g",
        "price": 45,
        "status": "Linha Regular",
        "description": "Ajuda a reduzir olheiras, bolsas e rugas na região dos olhos, uma área mais fina e delicada, que precisa de cuidados especiais.",
        "gridList": [
            {
                "SKU": "10-060198"
            }
        ]
    },
    {
        "id": 61,
        "session": "Cuidados com a Pele",
        "line": "MKMen",
        "image": "10-020104.jpg",
        "points": 18,
        "title": "Fragrância Corporal em Spray - 113 g",
        "price": 41,
        "status": "Linha Regular",
        "extra": "compra até 31/12/13",
        "description": "Leve e refrescante, é ideal para ser usada diariamente.",
        "gridList": [
            {
                "SKU": "10-020104"
            }
        ]
    },
    {
        "id": 62,
        "session": "Cuidados com a Pele",
        "line": "MKMen",
        "image": "10-055844.jpg",
        "points": 21,
        "title": "Sabonete Facial - 113 g",
        "price": 38,
        "status": "Linha Regular",
        "description": "Limpa a pele, iniciando o processo de redução dos sinais visíveis do envelhecimento.",
        "gridList": [
            {
                "SKU": "10-055844"
            }
        ]
    },
    {
        "id": 63,
        "session": "Cuidados com a Pele",
        "line": "MKMen",
        "image": "10-010336.jpg",
        "points": 19,
        "title": "Espuma para Barbear - 184 g",
        "price": 37,
        "status": "Linha Regular",
        "description": "Amacia a pele e ajuda a reduzir a irritação causada pela lâmina de barbear.",
        "gridList": [
            {
                "SKU": "10-010336"
            }
        ]
    },
    {
        "id": 64,
        "session": "Cuidados com a Pele",
        "line": "MKMen",
        "image": "10-010338.jpg",
        "points": 18,
        "title": "Gel Refrescante Pós Barba - 73 ml",
        "price": 33,
        "status": "Linha Regular",
        "description": "Acalma a pele e ameniza a irritação causada pela lâmina.",
        "gridList": [
            {
                "SKU": "10-010338"
            }
        ]
    },
    {
        "id": 65,
        "session": "Cuidados com a Pele",
        "line": "MKMen",
        "image": "10-010332.jpg",
        "points": 30,
        "title": "Loção Hidratante com FPS 25 - 88 ml",
        "price": 55,
        "status": "Linha Regular",
        "extra": "compra até 31/12/13",
        "description": "Hidrata e protege contra os raios UVA/UVB, que podem causar o envelhecimento prococe da pele.",
        "gridList": [
            {
                "SKU": "10-010332"
            }
        ]
    },
    {
        "id": 66,
        "session": "Cuidados com a Pele",
        "line": "Cuidados Personalizados",
        "image": "10-029739.jpg",
        "points": 29,
        "title": "Gel Suavizante para a Área dos Olhos - 11 g",
        "price": 53,
        "status": "Linha Regular",
        "description": "Contém extratos botânicos que ajudam a reduzir a aparência de inchaço na região dos olhos.",
        "gridList": [
            {
                "SKU": "10-029739"
            }
        ]
    },
    {
        "id": 67,
        "session": "Cuidados com a Pele",
        "line": "Cuidados Personalizados",
        "image": "10-998000.jpg",
        "points": 50,
        "title": "Kit Lábios de Seda Satin Lips",
        "price": 69,
        "status": "Linha Regular",
        "description": "Esfolia e hidrata os lábios, deixando-os macios e suaves.",
        "gridList": [
            {
                "SKU": "10-998000"
            }
        ]
    },
    {
        "id": 68,
        "session": "Cuidados com a Pele",
        "line": "Cuidados Personalizados",
        "image": "10-042792.jpg",
        "points": 25,
        "title": "Bálsamo para os Lábios Satin Lips - 8 g",
        "price": 39,
        "status": "Linha Regular",
        "gridList": [
            {
                "SKU": "10-042792"
            }
        ]
    },
    {
        "id": 69,
        "session": "Cuidados com a Pele",
        "line": "Cuidados Personalizados",
        "image": "10-042796.jpg",
        "points": 25,
        "title": "Máscara para os Lábios Satin Lips - 8 g",
        "price": 39,
        "status": "Linha Regular",
        "gridList": [
            {
                "SKU": "10-042796"
            }
        ]
    },
    {
        "id": 70,
        "session": "Cuidados com a Pele",
        "line": "Cuidados Personalizados",
        "image": "10-031573.jpg",
        "points": 29,
        "title": "Loção Antibrilho e Oleosidade - 17 ml",
        "price": 45,
        "status": "Linha Regular",
        "description": "Absorve a oleosidade e ajuda a controlar o brilho por até oito horas.",
        "gridList": [
            {
                "SKU": "10-031573"
            }
        ]
    },
    {
        "id": 71,
        "session": "Cuidados com a Pele",
        "line": "Cuidados Personalizados",
        "image": "10-041758.jpg",
        "points": 17,
        "title": "Lenços de Papel Antibrilho da Pele - 75 unidades",
        "price": 28,
        "status": "Linha Regular",
        "description": "Remove o brilho e ajuda a manter a maquiagem impecável.",
        "gridList": [
            {
                "SKU": "10-041758"
            }
        ]
    },
    {
        "id": 72,
        "session": "Cuidados com a Pele",
        "line": "Cuidados Personalizados",
        "image": "10-045655.jpg",
        "points": 30,
        "title": "Hidratante Noturno Extra Emoliente - 60 g",
        "price": 47,
        "status": "Linha Regular",
        "description": "Ajuda a manter a hidratação natural da pele e repõe a umidade em áreas ressecadas como mãos, cotovelos, joelhos e pés.",
        "gridList": [
            {
                "SKU": "10-045655"
            }
        ]
    },
    {
        "id": 73,
        "session": "Cuidados com a Pele",
        "line": "Cuidados Personalizados",
        "image": "10-031551.jpg",
        "points": 51,
        "title": "Gel Hidratante sem Óleo - 51 g",
        "price": 77,
        "status": "Linha Regular",
        "description": "É absorvido rapidamente, mantém a hidratação e a umidade da pele por até dez horas.",
        "gridList": [
            {
                "SKU": "10-031551"
            }
        ]
    },
    {
        "id": 74,
        "session": "SPA e Fragrâncias",
        "line": "Cuidados com o Corpo",
        "image": "10-039418.jpg",
        "points": 20,
        "title": "Creme Esfoliante Satin Body - 185 g",
        "price": 35,
        "status": "Linha Regular",
        "description": "Esfolia a pele do corpo e elimina a textura ressecada.",
        "gridList": [
            {
                "SKU": "10-039418"
            }
        ]
    },
    {
        "id": 75,
        "session": "SPA e Fragrâncias",
        "line": "Cuidados com o Corpo",
        "image": "10-039409.jpg",
        "points": 20,
        "title": "Gel para o Corpo 2 em 1 Satin Body - 192 ml",
        "price": 35,
        "status": "Linha Regular",
        "description": "Limpa a pele e facilita a depilação.",
        "gridList": [
            {
                "SKU": "10-039409"
            }
        ]
    },
    {
        "id": 76,
        "session": "SPA e Fragrâncias",
        "line": "Cuidados com o Corpo",
        "image": "10-039413.jpg",
        "points": 20,
        "title": "Loção Hidratante Satin Body - 192 ml",
        "price": 35,
        "status": "Linha Regular",
        "description": "Proporciona hidratação por até vinte e quatro horas.",
        "gridList": [
            {
                "SKU": "10-039413"
            }
        ]
    },
    {
        "id": 77,
        "session": "SPA e Fragrâncias",
        "line": "Cuidados com o Corpo",
        "image": "10-031832.jpg",
        "points": 19,
        "title": "Creme para as Mãos Satin Hands - 85 g",
        "price": 32,
        "status": "Linha Regular",
        "description": "Fórmula que deixa a pele instantaneamente macia e hidratada por até vinte e quatro horas.",
        "gridList": [
            {
                "SKU": "10-042836",
                "option": "Pêssego"
            },
            {
                "SKU": "10-031832",
                "option": "Livre de Fragrância"
            }
        ]
    },
    {
        "id": 78,
        "session": "SPA e Fragrâncias",
        "line": "Cuidados com o Corpo",
        "image": "10-032362.jpg",
        "points": 67,
        "title": "Kit Mãos de Seda",
        "price": 132,
        "status": "Linha Regular",
        "description": "O Kit inclui o Esfoliante para as Mãos Satin Smoothie, o Creme Extra Emoliente e o Creme para as Mãos em uma prática sacola.",
        "gridList": [
            {
                "SKU": "10-033897",
                "option": "Pêssego"
            },
            {
                "SKU": "10-032362",
                "option": "Livre de Fragrância"
            }
        ]
    },
    {
        "id": 79,
        "session": "SPA e Fragrâncias",
        "line": "Cuidados com o Corpo",
        "image": "10-014096.jpg",
        "points": 19,
        "title": "Loção Energizante para os Pés e Pernas Mint Bliss - 88 ml",
        "price": 42,
        "status": "Linha Regular",
        "description": "Uma fórmula de menta refrescante que ajuda a aliviar o cansaço dos pés e pernas.",
        "gridList": [
            {
                "SKU": "10-014096"
            }
        ]
    },
    {
        "id": 80,
        "session": "Cuidados com a Pele",
        "line": "Solar",
        "image": "10-049423.jpg",
        "points": 24,
        "title": "Loção Corporal Autobronzeadora - 118 ml",
        "price": 44,
        "status": "Linha Regular",
        "description": "Hidrata a pele e proporciona um bronzeado sutil, que se desenvolve gradualmente para um visual totalmente natural. Não possui fator de proteção solar.",
        "gridList": [
            {
                "SKU": "10-049423"
            }
        ]
    },
    {
        "id": 81,
        "session": "Cuidados com a Pele",
        "line": "Solar",
        "image": "10-042829.jpg",
        "points": 28,
        "title": "Protetor Solar com FPS 30 - 118 ml",
        "price": 54,
        "status": "Linha Regular",
        "description": "Fórmula leve e livre de óleo, para o rosto e para o corpo, que proporciona proteção contra os raios UVA/UVB. À prova d'água e resistente ao suor por até oitenta minutos.",
        "gridList": [
            {
                "SKU": "10-042829"
            }
        ]
    },
    {
        "id": 82,
        "session": "Cuidados com a Pele",
        "line": "Solar",
        "image": "10-050165.jpg",
        "points": 20,
        "title": "Gel Restaurador Pós Sol - 192 ml",
        "price": 39,
        "status": "Linha Regular",
        "description": "Formulado com extratos botânicos ricos em antioxidantes, este gel é absorvido rapidamente, repondo a hidratação.",
        "gridList": [
            {
                "SKU": "10-050165"
            }
        ]
    },
    {
        "id": 83,
        "session": "Cuidados com a Pele",
        "line": "Solar",
        "image": "10-049430.jpg",
        "points": 13,
        "title": "Protetor Solar para os Lábios com FPS 15 - 4,5 g",
        "price": 23,
        "status": "Linha Regular",
        "description": "Ajuda a proteger os lábios dos efeitos nocivos da radiação solar.",
        "gridList": [
            {
                "SKU": "10-049430"
            }
        ]
    },
    {
        "id": 84,
        "session": "Maquiagem",
        "line": "Maquiagem",
        "image": "10-059507.jpg",
        "points": 27,
        "title": "Base Líquida TimeWise - Acabamento Matte - 29 ml",
        "price": 54,
        "status": "Linha Regular",
        "description": "Fórmula leve, que ajuda a controlar o excesso de oleosidade e o brilho durante todo o dia. Diminui a aparência de rugas e linhas finas.",
        "gridList": [
            {
                "SKU": "10-059508",
                "option": "Ivory 6"
            },
            {
                "SKU": "10-059509",
                "option": "Ivory 7"
            },
            {
                "SKU": "10-059510",
                "option": "Beige 1"
            },
            {
                "SKU": "10-059511",
                "option": "Beige 2"
            },
            {
                "SKU": "10-059512",
                "option": "Beige 3"
            },
            {
                "SKU": "10-059513",
                "option": "Beige 4"
            },
            {
                "SKU": "10-059514",
                "option": "Beige 5"
            },
            {
                "SKU": "10-059515",
                "option": "Beige 6"
            },
            {
                "SKU": "10-059519",
                "option": "Bronze 1"
            },
            {
                "SKU": "10-059520",
                "option": "Bronze 2"
            },
            {
                "SKU": "10-059522",
                "option": "Bronze 4"
            },
            {
                "SKU": "10-059523",
                "option": "Bronze 5"
            },
            {
                "SKU": "10-059525",
                "option": "Bronze 7"
            },
            {
                "SKU": "10-059507",
                "option": "Ivory 5"
            }
        ]
    },
    {
        "id": 85,
        "session": "Maquiagem",
        "line": "Maquiagem",
        "image": "10-059978.jpg",
        "points": 27,
        "title": "Base Líquida TimeWise - Acabamento Luminoso - 29 ml",
        "price": 54,
        "status": "Linha Regular",
        "description": "Proporciona uma pele com luminosidade e visual radiante com a melhora do aspecto da textura da pele.",
        "gridList": [
            {
                "SKU": "10-059979",
                "option": "Ivory 6"
            },
            {
                "SKU": "10-059980",
                "option": "Ivory 7"
            },
            {
                "SKU": "10-059527",
                "option": "Beige 1"
            },
            {
                "SKU": "10-059528",
                "option": "Beige 2"
            },
            {
                "SKU": "10-059529",
                "option": "Beige 3"
            },
            {
                "SKU": "10-059530",
                "option": "Beige 4"
            },
            {
                "SKU": "10-059531",
                "option": "Beige 5"
            },
            {
                "SKU": "10-059532",
                "option": "Beige 6"
            },
            {
                "SKU": "10-059535",
                "option": "Bronze 1"
            },
            {
                "SKU": "10-059536",
                "option": "Bronze 2"
            },
            {
                "SKU": "10-059538",
                "option": "Bronze 4"
            },
            {
                "SKU": "10-059539",
                "option": "Bronze 5"
            },
            {
                "SKU": "10-059541",
                "option": "Bronze 7"
            },
            {
                "SKU": "10-059978",
                "option": "Ivory 5"
            }
        ]
    },
    {
        "id": 86,
        "session": "Maquiagem",
        "line": "Maquiagem",
        "image": "10-041998.jpg",
        "points": 20,
        "title": "Base de Cobertura Média - 29 ml",
        "price": 46,
        "status": "Linha Regular",
        "description": "Proporciona uma cor verdadeira e duradoura, além de ajudar a controlar o excesso de oleosidade por até oito horas.",
        "gridList": [
            {
                "SKU": "10-042001",
                "option": "Ivory 204"
            },
            {
                "SKU": "10-042002",
                "option": "Beige 300"
            },
            {
                "SKU": "10-042003",
                "option": "Beige 302"
            },
            {
                "SKU": "10-042004",
                "option": "Beige 304"
            },
            {
                "SKU": "10-042006",
                "option": "Beige 400"
            },
            {
                "SKU": "10-042007",
                "option": "Beige 402"
            },
            {
                "SKU": "10-042009",
                "option": "Bronze 500"
            },
            {
                "SKU": "10-041998",
                "option": "Ivory 200"
            }
        ]
    },
    {
        "id": 87,
        "session": "Maquiagem",
        "line": "Maquiagem",
        "image": "10-040984.jpg",
        "points": 23,
        "title": "Base em Pó Mineral - 8 g",
        "price": 54,
        "status": "Linha Regular",
        "description": "Um pó leve que se espalha facilmente para um visual impecável.",
        "gridList": [
            {
                "SKU": "10-040985",
                "option": "Ivory 2"
            },
            {
                "SKU": "10-040987",
                "option": "Beige 1"
            },
            {
                "SKU": "10-040989",
                "option": "Beige 2"
            },
            {
                "SKU": "10-040990",
                "option": "Bronze 1"
            },
            {
                "SKU": "10-040991",
                "option": "Bronze 2"
            },
            {
                "SKU": "10-040984",
                "option": "Ivory 1"
            }
        ]
    },
    {
        "id": 88,
        "session": "Maquiagem",
        "line": "Maquiagem",
        "image": "10-031512.jpg",
        "points": 23,
        "title": "Hidratante Tonalizante com FPS 20 - 43 ml",
        "price": 47,
        "status": "Linha Regular",
        "description": "Três benefícios em um - cobertura translúcida, hidratação livre de óleo e proteção contra os raios UVA e UVB.",
        "gridList": [
            {
                "SKU": "10-031513",
                "option": "Beige 1"
            },
            {
                "SKU": "10-031514",
                "option": "Beige 2"
            },
            {
                "SKU": "10-031515",
                "option": "Bronze 1"
            },
            {
                "SKU": "10-031512",
                "option": "Ivory 2"
            }
        ]
    },
    {
        "id": 89,
        "session": "Maquiagem",
        "line": "MK at Play",
        "image": "10-062144.jpg",
        "points": 15,
        "title": "Trio de Sombras Efeito Brilho - 2 g",
        "price": 29,
        "status": "Linha Regular",
        "description": "Muito brilho e ótima pigmentação. Três sombras em apenas um produto.",
        "gridList": [
            {
                "SKU": "10-062145",
                "option": "Ocean View"
            },
            {
                "SKU": "10-062143",
                "option": "On the Horizon"
            },
            {
                "SKU": "10-062146",
                "option": "Tuxedo"
            },
            {
                "SKU": "10-062144",
                "option": "Earth Bound"
            }
        ]
    },
    {
        "id": 90,
        "session": "Maquiagem",
        "line": "MK at Play",
        "image": "10-067803.jpg",
        "points": 11,
        "title": "Lápis Sombra - 2,5 g",
        "price": 20,
        "status": "Linha Regular",
        "description": "Sua fórmula ultra cremosa não acumula nas pálpebras. Cores divertidas e com acabamento metalizado.",
        "gridList": [
            {
                "SKU": "10-067805",
                "option": "Gold Mine"
            },
            {
                "SKU": "10-067801",
                "option": "In the Navy"
            },
            {
                "SKU": "10-067804",
                "option": "Purple Smoke"
            },
            {
                "SKU": "10-067803",
                "option": "Green Tea"
            }
        ]
    },
    {
        "id": 91,
        "session": "Maquiagem",
        "line": "MK at Play",
        "image": "10-062089.jpg",
        "points": 9,
        "title": "Gloss Labial Jelly - 9,5 ml",
        "price": 18,
        "status": "Linha Regular",
        "description": "Lábios macios e glamorosos com cores intensas e brilhantes.",
        "gridList": [
            {
                "SKU": "10-062088",
                "option": "Crushed Plum"
            },
            {
                "SKU": "10-062087",
                "option": "Hot Tamale"
            },
            {
                "SKU": "10-062086",
                "option": "Teddy Bare"
            },
            {
                "SKU": "10-062089",
                "option": "Berry Me"
            }
        ]
    },
    {
        "id": 92,
        "session": "Maquiagem",
        "line": "MK at Play",
        "image": "10-067790.jpg",
        "points": 11,
        "title": "Lápis Batom - 2,5 g",
        "price": 20,
        "status": "Linha Regular",
        "description": "Cores marcantes com acabamento luminoso. Sua fórmula desliza facilmente e não borra durante o dia.",
        "gridList": [
            {
                "SKU": "10-067788",
                "option": "Perfect Pink"
            },
            {
                "SKU": "10-067783",
                "option": "Toasted"
            },
            {
                "SKU": "10-067789",
                "option": "Violet Love"
            },
            {
                "SKU": "10-067790",
                "option": "Candied Apple"
            }
        ]
    },
    {
        "id": 93,
        "session": "Maquiagem",
        "line": "Maquiagem",
        "image": "10-023467.jpg",
        "points": 20,
        "title": "Corretivo - 8,5 g",
        "price": 32,
        "status": "Linha Regular",
        "description": "Fórmula cremosa de longa duração que disfarça pequenas imperfeições.",
        "gridList": [
            {
                "SKU": "10-023468",
                "option": "Ivory 2"
            },
            {
                "SKU": "10-023469",
                "option": "Beige 1"
            },
            {
                "SKU": "10-023470",
                "option": "Beige 2"
            },
            {
                "SKU": "10-023471",
                "option": "Bronze 1"
            },
            {
                "SKU": "10-023472",
                "option": "Bronze 2"
            },
            {
                "SKU": "10-027243",
                "option": "Yellow"
            },
            {
                "SKU": "10-023467",
                "option": "Ivory 1"
            }
        ]
    },
    {
        "id": 94,
        "session": "Maquiagem",
        "line": "Maquiagem",
        "image": "10-015136.jpg",
        "points": 21,
        "title": "Pó Mineral Compacto (Refil) - 9 g",
        "price": 39,
        "status": "Linha Regular",
        "description": "Um pó leve que proporciona uma camada translúcida de cobertura para controlar a oleosidade.",
        "gridList": [
            {
                "SKU": "10-015137",
                "option": "Beige 1"
            },
            {
                "SKU": "10-015138",
                "option": "Beige 2"
            },
            {
                "SKU": "10-015139",
                "option": "Bronze 1"
            },
            {
                "SKU": "10-015140",
                "option": "Bronze 2"
            },
            {
                "SKU": "10-015136",
                "option": "Ivory 2"
            }
        ]
    },
    {
        "id": 95,
        "session": "Maquiagem",
        "line": "Maquiagem",
        "image": "10-019029.jpg",
        "points": 18,
        "title": "Iluminador Facial - 1,3 ml",
        "price": 42,
        "status": "Linha Regular",
        "description": "Sua fórmula contém partículas esféricas que refletem a luz em várias direções, iluminando as áreas sombreadas.",
        "gridList": [
            {
                "SKU": "10-019031",
                "option": "Tom 3"
            },
            {
                "SKU": "10-019029",
                "option": "Tom 2"
            }
        ]
    },
    {
        "id": 96,
        "session": "Maquiagem",
        "line": "Maquiagem",
        "image": "10-013008.jpg",
        "points": 12,
        "title": "Sombra Mineral (Refil) - 1,4 g",
        "price": 21,
        "status": "Linha Regular",
        "description": "São tonalidades vibrantes e de longa duração em fórmula mineral. Proporcionam cores intensas, que não acumulam nas pálpebras, e são ideais para qualquer tom de pele.",
        "gridList": [
            {
                "SKU": "10-030111",
                "option": "Azure"
            },
            {
                "SKU": "10-028589",
                "option": "Black Pearl"
            },
            {
                "SKU": "10-013050",
                "option": "Blue Metal"
            },
            {
                "SKU": "10-013035",
                "option": "Chocolate Kiss"
            },
            {
                "SKU": "10-013038",
                "option": "Cinnabar"
            },
            {
                "SKU": "10-046687",
                "option": "Classic Navy"
            },
            {
                "SKU": "10-013026",
                "option": "Coal"
            },
            {
                "SKU": "10-013044",
                "option": "Crystalline"
            },
            {
                "SKU": "10-013056",
                "option": "Denim Frost"
            },
            {
                "SKU": "10-030110",
                "option": "Emerald"
            },
            {
                "SKU": "10-013047",
                "option": "Espresso"
            },
            {
                "SKU": "10-046684",
                "option": "Gold Coast"
            },
            {
                "SKU": "10-013080",
                "option": "Granite"
            },
            {
                "SKU": "10-013032",
                "option": "Honey Spice"
            },
            {
                "SKU": "10-013095",
                "option": "Iris"
            },
            {
                "SKU": "10-013062",
                "option": "Ivy Garden"
            },
            {
                "SKU": "10-046680",
                "option": "Jade"
            },
            {
                "SKU": "10-030107",
                "option": "Lavender Fog"
            },
            {
                "SKU": "10-013005",
                "option": "Lemongrass"
            },
            {
                "SKU": "10-028588",
                "option": "Midnight Star"
            },
            {
                "SKU": "10-030106",
                "option": "Peacock Blue"
            },
            {
                "SKU": "10-013074",
                "option": "Precious Pink"
            },
            {
                "SKU": "10-026297",
                "option": "Silver Satin"
            },
            {
                "SKU": "10-046683",
                "option": "Sterling"
            },
            {
                "SKU": "10-013101",
                "option": "Sweet Plum"
            },
            {
                "SKU": "10-046681",
                "option": "Truffle"
            },
            {
                "SKU": "10-026292",
                "option": "White Lily"
            },
            {
                "SKU": "10-013008",
                "option": "Amber Blaze"
            }
        ]
    },
    {
        "id": 97,
        "session": "Maquiagem",
        "line": "Maquiagem",
        "image": "10-017587.jpg",
        "points": 23,
        "title": "Delineador Líquido para os Olhos - Preto - 3 ml",
        "price": 35,
        "status": "Linha Regular",
        "description": "Cor intensa e duradoura. O aplicador especial torna a aplicação super fácil.",
        "gridList": [
            {
                "SKU": "10-017587"
            }
        ]
    },
    {
        "id": 98,
        "session": "Maquiagem",
        "line": "Maquiagem",
        "image": "10-051607.jpg",
        "points": 18,
        "title": "Lápis Retrátil para os Olhos - 0,28 g",
        "price": 33,
        "status": "Linha Regular",
        "description": "Lápis de mecanismo retrátil com fórmula suave e a prova d'água. Vem com um exclusivo apontador na tampa.",
        "gridList": [
            {
                "SKU": "10-051611",
                "option": "Violet Ink"
            },
            {
                "SKU": "10-051608",
                "option": "Deep Brown"
            },
            {
                "SKU": "10-051610",
                "option": "Dark Denim"
            },
            {
                "SKU": "10-051609",
                "option": "Steely"
            },
            {
                "SKU": "10-051613",
                "option": "Rich Jade"
            },
            {
                "SKU": "10-051607",
                "option": "Black"
            }
        ]
    },
    {
        "id": 99,
        "session": "Maquiagem",
        "line": "Sobrancelhas",
        "image": "10-027859.jpg",
        "points": 14,
        "title": "Gel para Sobrancelhas",
        "price": 27,
        "status": "Linha Regular",
        "description": "Ele fixa a sobrancelha no lugar certo e dá um aspecto mais encorpado aos fios.",
        "gridList": [
            {
                "SKU": "10-027859"
            }
        ]
    },
    {
        "id": 100,
        "session": "Maquiagem",
        "line": "Sobrancelhas",
        "image": "10-027861.jpg",
        "points": 8,
        "title": "Kit para Sobrancelhas",
        "price": 15,
        "status": "Linha Regular",
        "description": "Inclui: Mini pinça, mini pincel e mini escova.",
        "gridList": [
            {
                "SKU": "10-027861"
            }
        ]
    },
    {
        "id": 101,
        "session": "Maquiagem",
        "line": "Maquiagem",
        "image": "10-034730.jpg",
        "points": 18,
        "title": "Lápis Delineador para Sobrancelhas - 1,13 g",
        "price": 30,
        "status": "Linha Regular",
        "description": "Fórmula cremosa, de longa duração e à prova d'água, para um visual bem definido.",
        "gridList": [
            {
                "SKU": "10-034731",
                "option": "Brunette"
            },
            {
                "SKU": "10-034730",
                "option": "Classic Blonde"
            }
        ]
    },
    {
        "id": 102,
        "session": "Maquiagem",
        "line": "Maquiagem",
        "image": "10-035651.jpg",
        "points": 25,
        "title": "Ultimate Máscara para Cílios - 8 g",
        "price": 51,
        "status": "Linha Regular",
        "description": "Fórmula exclusiva, para cílios marcantes com até cinco vezes mais volume.",
        "gridList": [
            {
                "SKU": "10-035651",
                "option": "Preta"
            }
        ]
    },
    {
        "id": 103,
        "session": "Maquiagem",
        "line": "Maquiagem",
        "image": "10-049293.jpg",
        "points": 25,
        "title": "Máscara para Cílios Lash Love - 9 g",
        "price": 51,
        "status": "Linha Regular",
        "description": "Define, protege e proporciona volume ideal aos cílios.",
        "gridList": [
            {
                "SKU": "10-049293",
                "option": "Preta"
            }
        ]
    },
    {
        "id": 104,
        "session": "Maquiagem",
        "line": "Maquiagem",
        "image": "10-054563.png",
        "points": 25,
        "title": "Máscara Alongadora para Cílios Lash Love - 8 g",
        "price": 51,
        "status": "Linha Regular",
        "description": "Cílios longos, fortes e definidos.",
        "gridList": [
            {
                "SKU": "10-054563",
                "option": "Preta"
            }
        ]
    },
    {
        "id": 105,
        "session": "Maquiagem",
        "line": "Maquiagem",
        "image": "10-049289.jpg",
        "points": 25,
        "title": "Máscara para Cílios Lash Love à Prova D'água - 9 g",
        "price": 51,
        "status": "Linha Regular",
        "description": "Define, protege e proporciona volume ideal aos cílios em fórmula resistente à água.",
        "gridList": [
            {
                "SKU": "10-049289",
                "option": "Preta"
            }
        ]
    },
    {
        "id": 106,
        "session": "Maquiagem",
        "line": "Maquiagem",
        "image": "10-046176.jpg",
        "points": 19,
        "title": "Máscara Incolor Primer para Cílios - 8 g",
        "price": 37,
        "status": "Linha Regular",
        "description": "Dois produtos em um: Máscara Incolor + Primer para Cílios.",
        "gridList": [
            {
                "SKU": "10-046176"
            }
        ]
    },
    {
        "id": 107,
        "session": "Maquiagem",
        "line": "Cuidados Personalizados",
        "image": "10-046188.jpeg",
        "points": 48,
        "title": "Sérum Fortalecedor de Cílios e Sobrancelhas - 4,5 g",
        "price": 89,
        "status": "Linha Regular",
        "description": "Antes de dormir, aplique nos cílios superiores e nas sobrancelhas.",
        "gridList": [
            {
                "SKU": "10-046188"
            }
        ]
    },
    {
        "id": 108,
        "session": "Maquiagem",
        "line": "Cuidados Personalizados",
        "image": "10-042768.jpg",
        "points": 26,
        "title": "Demaquilante para a Área dos Olhos - 110 ml",
        "price": 51,
        "status": "Linha Regular",
        "description": "Remove delicadamente a maquiagem dos olhos.",
        "gridList": [
            {
                "SKU": "10-042768"
            }
        ]
    },
    {
        "id": 109,
        "session": "Maquiagem",
        "line": "Cuidados Personalizados",
        "image": "10-016960.jpg",
        "points": 28,
        "title": "Eye Primer Fixador de Sombra - 8,5 g",
        "price": 42,
        "status": "Linha Regular",
        "description": "Fórmula à prova d'água que cria uma base transparente que prolonga e intensifica a cor da sombra.",
        "gridList": [
            {
                "SKU": "10-016960"
            }
        ]
    },
    {
        "id": 110,
        "session": "Maquiagem",
        "line": "Maquiagem",
        "image": "10-060182.jpg",
        "points": 21,
        "title": "Pó Solto Translúcido - 11 g",
        "price": 49,
        "status": "Linha Regular",
        "description": "Proporciona um acabamento natural e controla a oleosidade e o brilho durante todo o dia sem obstruir os poros ou acumular nas linhas finas.",
        "gridList": [
            {
                "SKU": "10-060182"
            }
        ]
    },
    {
        "id": 111,
        "session": "Maquiagem",
        "line": "Maquiagem",
        "image": "10-012983.jpg",
        "points": 18,
        "title": "Blush Mineral (Refil) - 5 g",
        "price": 32,
        "status": "Linha Regular",
        "description": "Fórmula mineral e cores versáteis e resistentes, que ficam bem em qualquer tom de pele.",
        "gridList": [
            {
                "SKU": "10-012977",
                "option": "Cinnamon Stick"
            },
            {
                "SKU": "10-026286",
                "option": "Citrus Bloom"
            },
            {
                "SKU": "10-012965",
                "option": "Golden Copper"
            },
            {
                "SKU": "10-012974",
                "option": "Shy Blush"
            },
            {
                "SKU": "10-012950",
                "option": "Sparkling Cider"
            },
            {
                "SKU": "10-012980",
                "option": "Strawberry Cream"
            },
            {
                "SKU": "10-016243",
                "option": "Sunny Spice"
            },
            {
                "SKU": "10-012983",
                "option": "Cherry Blossom"
            }
        ]
    },
    {
        "id": 112,
        "session": "Maquiagem",
        "line": "Maquiagem",
        "image": "10-031780.jpg",
        "points": 19,
        "title": "Blush em Creme - 2,1 g",
        "price": 35,
        "status": "Linha Regular",
        "description": "Fórmula cremosa que desliza facilmente na pele e proporciona um acabamento aveludado.",
        "gridList": [
            {
                "SKU": "10-031782",
                "option": "Sheer Bliss"
            },
            {
                "SKU": "10-031780",
                "option": "Cranberry"
            }
        ]
    },
    {
        "id": 113,
        "session": "Maquiagem",
        "line": "Maquiagem",
        "image": "10-016165.jpg",
        "points": 19,
        "title": "Pó Mineral Bronzeador Matte (Refil) - 4,5 g",
        "price": 35,
        "status": "Linha Regular",
        "description": "As tonalidades com brilho trazem uma luminosidade natural ao rosto e as tonalidades matte aquecem o visual.",
        "gridList": [
            {
                "SKU": "10-016167",
                "option": "Bronze Diva"
            },
            {
                "SKU": "10-016165",
                "option": "Sandstone"
            }
        ]
    },
    {
        "id": 114,
        "session": "Maquiagem",
        "line": "Maquiagem",
        "image": "10-016610.jpg",
        "points": 19,
        "title": "Pó Mineral Bronzeador com Brilho (Refil) - 4,5 g",
        "price": 35,
        "status": "Linha Regular",
        "gridList": [
            {
                "SKU": "10-016611",
                "option": "Canyon Gold"
            },
            {
                "SKU": "10-016610",
                "option": "Desert Sun"
            }
        ]
    },
    {
        "id": 115,
        "session": "Maquiagem",
        "line": "Maquiagem",
        "image": "10-016615.jpg",
        "points": 19,
        "title": "Pó Mineral Iluminador (Refil) - 4,5 g",
        "price": 35,
        "status": "Linha Regular",
        "description": "Deixe a sua pele ainda mais iluminada e radiante.",
        "gridList": [
            {
                "SKU": "10-016615",
                "option": "Pink Stardust"
            }
        ]
    },
    {
        "id": 116,
        "session": "Maquiagem",
        "line": "Maquiagem",
        "image": "10-051595.jpg",
        "points": 18,
        "title": "Lápis Retrátil para os Lábios - 0,28 g",
        "price": 31,
        "status": "Linha Regular",
        "description": "Uma fórmula leve e à prova d'água, em uma prática embalagem retrátil. Desliza suavemente para uma aplicação uniforme, vem com um exclusivo apontador na tampa.",
        "gridList": [
            {
                "SKU": "10-051589",
                "option": "Cappuccino"
            },
            {
                "SKU": "10-051587",
                "option": "Neutral"
            },
            {
                "SKU": "10-051592",
                "option": "Soft Blush"
            },
            {
                "SKU": "10-051595",
                "option": "Clear"
            }
        ]
    },
    {
        "id": 117,
        "session": "Maquiagem",
        "line": "Maquiagem",
        "image": "10-054822.png",
        "points": 26,
        "title": "Batom True Dimensions - 3,3 g",
        "price": 47,
        "status": "Linha Regular",
        "description": "Proporcione uma nova dimensão aos seus lábios com uma fórmula avançada em uma sofisticada embalagem metálica.",
        "gridList": [
            {
                "SKU": "10-054828",
                "option": "Firecracker"
            },
            {
                "SKU": "10-054823",
                "option": "First Blush"
            },
            {
                "SKU": "10-054825",
                "option": "Natural Beauté"
            },
            {
                "SKU": "10-054820",
                "option": "Pink Chérie"
            },
            {
                "SKU": "10-054830",
                "option": "Rosette"
            },
            {
                "SKU": "10-054829",
                "option": "Sizzling Red"
            },
            {
                "SKU": "10-054821",
                "option": "Wild About Pink"
            },
            {
                "SKU": "10-054822",
                "option": "Color Me Coral"
            }
        ]
    },
    {
        "id": 118,
        "session": "Maquiagem",
        "line": "Maquiagem",
        "image": "10-022936.jpg",
        "points": 19,
        "title": "Batom Cremoso - 3 g",
        "price": 35,
        "status": "Linha Regular",
        "description": "Sua fórmula de longa duração desliza pelos lábios com uma textura leve e cremosa, para um resultado impactante e duradouro. Enriquecido com Vitamina E que ajuda a proteger contra a ação dos radicais lives.",
        "gridList": [
            {
                "SKU": "10-022942",
                "option": "Apple Berry"
            },
            {
                "SKU": "10-022944",
                "option": "Berry Kiss"
            },
            {
                "SKU": "10-022958",
                "option": "Dusty Rose"
            },
            {
                "SKU": "10-022952",
                "option": "Frosted Rose"
            },
            {
                "SKU": "10-040717",
                "option": "Fuchsia"
            },
            {
                "SKU": "10-022937",
                "option": "Gingerbread"
            },
            {
                "SKU": "10-022961",
                "option": "Hibiscus"
            },
            {
                "SKU": "10-029478",
                "option": "Icy Peach"
            },
            {
                "SKU": "10-040707",
                "option": "Midnight Red"
            },
            {
                "SKU": "10-022957",
                "option": "Pink Melon"
            },
            {
                "SKU": "10-029472",
                "option": "Pink Passion"
            },
            {
                "SKU": "10-022960",
                "option": "Pink Satin"
            },
            {
                "SKU": "10-060356",
                "option": "Really Red"
            },
            {
                "SKU": "10-022965",
                "option": "Red"
            },
            {
                "SKU": "10-022945",
                "option": "Sheer Blush"
            },
            {
                "SKU": "10-022954",
                "option": "Shell"
            },
            {
                "SKU": "10-040712",
                "option": "Sunny Citrus"
            },
            {
                "SKU": "10-022963",
                "option": "Sweet Nectar"
            },
            {
                "SKU": "10-022955",
                "option": "Tanned"
            },
            {
                "SKU": "10-022953",
                "option": "Toffee"
            },
            {
                "SKU": "10-040710",
                "option": "Whisper"
            },
            {
                "SKU": "10-022936",
                "option": "Amber Suede"
            }
        ]
    },
    {
        "id": 119,
        "session": "Maquiagem",
        "line": "Maquiagem",
        "image": "10-051645.jpg",
        "points": 19,
        "title": "Batom Líquido - 7,6 g",
        "price": 35,
        "status": "Linha Regular",
        "description": "Combina cobertura impecável com a facilidade de aplicação de um brilho para os lábios.",
        "gridList": [
            {
                "SKU": "10-051647",
                "option": "Guava Punch"
            },
            {
                "SKU": "10-030424",
                "option": "Raspberry Ice"
            },
            {
                "SKU": "10-030425",
                "option": "Sherbet"
            },
            {
                "SKU": "10-030422",
                "option": "Malted"
            },
            {
                "SKU": "10-051645",
                "option": "Grapefruit"
            }
        ]
    },
    {
        "id": 120,
        "session": "Maquiagem",
        "line": "Maquiagem",
        "image": "10-052397.jpg",
        "points": 19,
        "title": "Brilho para os Lábios NouriShine Plus - 4,5 ml",
        "price": 33,
        "status": "Linha Regular",
        "description": "Protege, suaviza e hidrata os lábios. O produto proporciona ainda um brilho radiante em cores que estão sempre na moda.",
        "gridList": [
            {
                "SKU": "10-052405",
                "option": "Beach Bronze"
            },
            {
                "SKU": "10-052394",
                "option": "Berry Tart"
            },
            {
                "SKU": "10-052393",
                "option": "Icicle"
            },
            {
                "SKU": "10-052398",
                "option": "Mango Tango"
            },
            {
                "SKU": "10-057773",
                "option": "Pink Diamonds"
            },
            {
                "SKU": "10-052401",
                "option": "Pink Luster"
            },
            {
                "SKU": "10-053128",
                "option": "Rock'n'Red"
            },
            {
                "SKU": "10-053129",
                "option": "Shock Tart"
            },
            {
                "SKU": "10-053132",
                "option": "Sun Blossoms"
            },
            {
                "SKU": "10-052397",
                "option": "Au Naturel"
            }
        ]
    },
    {
        "id": 121,
        "session": "Maquiagem",
        "line": "Acessórios",
        "image": "10-040752.jpg",
        "points": 33,
        "title": "Mini Estojo Compacto (Vazio)",
        "price": 52,
        "status": "Linha Regular",
        "description": "Prático, cabe em qualquer lugar. O sistema de refil magnético possibilita diversas combinações, desde pó compacto, sombras, blush mineral ou pó bronzeador.",
        "gridList": [
            {
                "SKU": "10-040752"
            }
        ]
    },
    {
        "id": 122,
        "session": "Maquiagem",
        "line": "Acessórios",
        "image": "10-017362.jpg",
        "points": 41,
        "title": "Estojo Compacto (Vazio)",
        "price": 61,
        "status": "Linha Regular",
        "description": "O sistema de refil magnético permite que você customize infinitas combinações, com sombras, blushes, pós compactos ou pós bronzeadores. ",
        "gridList": [
            {
                "SKU": "10-017362"
            }
        ]
    },
    {
        "id": 123,
        "session": "Maquiagem",
        "line": "Acessórios",
        "image": "10-018587.jpg",
        "points": 71,
        "title": "Estojo Compacto Pro (Vazio)",
        "price": 110,
        "status": "Linha Regular",
        "description": "Tudo o que você precisa em um único estojo. Ele mantém todas as suas maquiagens e aplicadores organizados para que você crie uma maquiagem completa e customizável do início ao fim.",
        "gridList": [
            {
                "SKU": "10-018587"
            }
        ]
    },
    {
        "id": 124,
        "session": "Maquiagem",
        "line": "Acessórios",
        "image": "10-054132.jpg",
        "points": 63,
        "title": "Coleção de Pincéis",
        "price": 122,
        "status": "Linha Regular",
        "description": "Agora com o estojo em formato de maletinha. Seu novo design é moderno e traz uma nécessaire removível super prática para você levar seus produtos onde quiser.",
        "gridList": [
            {
                "SKU": "10-054132"
            }
        ]
    },
    {
        "id": 125,
        "session": "Maquiagem",
        "line": "Acessórios",
        "image": "10-053681.jpg",
        "points": 9,
        "title": "Pincel para Sombra",
        "price": 18,
        "status": "Linha Regular",
        "description": "Suas cerdas naturais aplicam a sombra com perfeição.",
        "gridList": [
            {
                "SKU": "10-053681"
            }
        ]
    },
    {
        "id": 126,
        "session": "Maquiagem",
        "line": "Acessórios",
        "image": "10-054040.jpg",
        "points": 19,
        "title": "Pincel para Base Líquida",
        "price": 36,
        "status": "Linha Regular",
        "description": "Perfeito para uma aplicação precisa de produtos com fórmulas cremosas e deposita a quantidade ideal de Base Líquida.",
        "gridList": [
            {
                "SKU": "10-054040"
            }
        ]
    },
    {
        "id": 127,
        "session": "Maquiagem",
        "line": "Acessórios",
        "image": "10-053678.jpg",
        "points": 19,
        "title": "Pincel para Pó Facial",
        "price": 36,
        "status": "Linha Regular",
        "description": "Suas cerdas macias e porosas permitem que a quantidade ideal do produto seja aplicada sobre a pele.",
        "gridList": [
            {
                "SKU": "10-053678"
            }
        ]
    },
    {
        "id": 128,
        "session": "Maquiagem",
        "line": "Acessórios",
        "image": "10-053680.jpg",
        "points": 9,
        "title": "Pincel para o Côncavo dos Olhos",
        "price": 18,
        "status": "Linha Regular",
        "description": "Perfeito para definir a linha do côncavo e dar mais profundidade ao olhar.",
        "gridList": [
            {
                "SKU": "10-053680"
            }
        ]
    },
    {
        "id": 129,
        "session": "Maquiagem",
        "line": "Acessórios",
        "image": "10-053675.jpg",
        "points": 9,
        "title": "Pincel para Esfumar",
        "price": 18,
        "status": "Linha Regular",
        "description": "Desenvolvido para um acabamento preciso, criando um look esfumado e dramático.",
        "gridList": [
            {
                "SKU": "10-053675"
            }
        ]
    },
    {
        "id": 130,
        "session": "Maquiagem",
        "line": "Acessórios",
        "image": "10-054041.jpg",
        "points": 9,
        "title": "Pincel para Corretivo e Sombra em Creme",
        "price": 18,
        "status": "Linha Regular",
        "description": "Cobertura impecável na aplicação de produtos de fórmulas cremosas.",
        "gridList": [
            {
                "SKU": "10-054041"
            }
        ]
    },
    {
        "id": 131,
        "session": "Maquiagem",
        "line": "Acessórios",
        "image": "10-053682.jpg",
        "points": 9,
        "title": "Pincel Duo Sobrancelha e Delineador",
        "price": 18,
        "status": "Linha Regular",
        "description": "Dois em um, com um lado você penteia e com o outro você delineia seus cílios e sobrancelhas.",
        "gridList": [
            {
                "SKU": "10-053682"
            }
        ]
    },
    {
        "id": 132,
        "session": "Maquiagem",
        "line": "Acessórios",
        "image": "10-054039.jpg",
        "points": 15,
        "title": "Pincel para Base em Pó Mineral",
        "price": 29,
        "status": "Linha Regular",
        "description": "Possui cerdas naturais de alta qualidade e ideais para aplicar fórmulas em pó.",
        "gridList": [
            {
                "SKU": "10-054039"
            }
        ]
    },
    {
        "id": 133,
        "session": "Maquiagem",
        "line": "Acessórios",
        "image": "10-053679.jpg",
        "points": 17,
        "title": "Pincel para Blush",
        "price": 32,
        "status": "Linha Regular",
        "description": "Cerdas macias, longas e de formato ideal para a aplicação do Blush Mineral.",
        "gridList": [
            {
                "SKU": "10-053679"
            }
        ]
    },
    {
        "id": 134,
        "session": "Maquiagem",
        "line": "Acessórios",
        "image": "10-015263.jpg",
        "points": 7,
        "title": "Pincel Compacto para Blush",
        "price": 9,
        "status": "Linha Regular",
        "gridList": [
            {
                "SKU": "10-015263"
            }
        ]
    },
    {
        "id": 135,
        "session": "Maquiagem",
        "line": "Acessórios",
        "image": "10-015264.jpg",
        "points": 7,
        "title": "Aplicadores para Sombra - 2 unidades",
        "price": 9,
        "status": "Linha Regular",
        "gridList": [
            {
                "SKU": "10-015264"
            }
        ]
    },
    {
        "id": 136,
        "session": "Maquiagem",
        "line": "Acessórios",
        "image": "10-015261.jpg",
        "points": 4,
        "title": "Esponjas Cosméticas - 2 unidades",
        "price": 11,
        "status": "Linha Regular",
        "gridList": [
            {
                "SKU": "10-015261"
            }
        ]
    },
    {
        "id": 137,
        "session": "Maquiagem",
        "line": "Acessórios",
        "image": "10-015262.jpg",
        "points": 5,
        "title": "Pincel para Pó Compacto",
        "price": 13,
        "status": "Linha Regular",
        "gridList": [
            {
                "SKU": "10-015262"
            }
        ]
    },
    {
        "id": 138,
        "session": "Maquiagem",
        "line": "Acessórios",
        "image": "10-015265.jpg",
        "points": 3,
        "title": "Pincel para Lábios (Retrátil)",
        "price": 10,
        "status": "Linha Regular",
        "gridList": [
            {
                "SKU": "10-015265"
            }
        ]
    },
    {
        "id": 139,
        "session": "Maquiagem",
        "line": "Acessórios",
        "image": "10-014209.jpg",
        "points": 7,
        "title": "Apontador Duplo",
        "price": 15,
        "status": "Linha Regular",
        "description": "Super versátil, esse apontador possui duas entradas.",
        "gridList": [
            {
                "SKU": "10-014209"
            }
        ]
    },
    {
        "id": 140,
        "session": "SPA e Fragrâncias",
        "line": "Perfumes",
        "image": "10-192900.jpg",
        "points": 41,
        "title": "Belara Eau de Parfum - 50 ml",
        "price": 88,
        "status": "Linha Regular",
        "description": "Uma revigorante combinação floral com notas de almíscar.",
        "gridList": [
            {
                "SKU": "10-192900"
            }
        ]
    },
    {
        "id": 141,
        "session": "SPA e Fragrâncias",
        "line": "Perfumes",
        "image": "10-012512.jpg",
        "points": 44,
        "title": "Bella Belara Eau de Parfum - 50 ml",
        "price": 88,
        "status": "Linha Regular",
        "description": "Uma exuberante fragrância floral frutal, com notas florais, frutas frescas e doces.",
        "gridList": [
            {
                "SKU": "10-012512"
            }
        ]
    },
    {
        "id": 142,
        "session": "SPA e Fragrâncias",
        "line": "Perfumes",
        "image": "10-397300.jpg",
        "points": 59,
        "title": "Elige Eau de Parfum - 50 ml",
        "price": 110,
        "status": "Linha Regular",
        "description": "Uma leve combinação de notas orientais, com exóticas essências de madeira.",
        "gridList": [
            {
                "SKU": "10-397300"
            }
        ]
    },
    {
        "id": 143,
        "session": "SPA e Fragrâncias",
        "line": "Perfumes",
        "image": "10-166700.jpg",
        "points": 48,
        "title": "Journey Eau de Parfum - 50 ml",
        "price": 99,
        "status": "Linha Regular",
        "description": "Uma fragrância floral suave, que combina aromas de menta e lírios.",
        "gridList": [
            {
                "SKU": "10-166700"
            }
        ]
    },
    {
        "id": 144,
        "session": "SPA e Fragrâncias",
        "line": "Perfumes",
        "image": "10-051949.jpg",
        "points": 59,
        "title": "Pink Diamonds Eau de Parfum - 60 ml",
        "price": 99,
        "status": "Linha Regular",
        "description": "Encante-se com essa fragrância floral, elaborada para mulheres elegantes e encantadoras.",
        "gridList": [
            {
                "SKU": "10-051949"
            }
        ]
    },
    {
        "id": 145,
        "session": "SPA e Fragrâncias",
        "line": "Perfumes",
        "image": "10-037726.jpg",
        "points": 52,
        "title": "Thinking of You Eau de Parfum - 29 ml",
        "price": 89,
        "status": "Linha Regular",
        "description": "Fragrância com notas frutais e florientais em uma embalagem especial, que permite escrever uma mensagem personalizada em seu interior.",
        "gridList": [
            {
                "SKU": "10-037726"
            }
        ]
    },
    {
        "id": 146,
        "session": "SPA e Fragrâncias",
        "line": "Perfumes",
        "image": "10-168700.jpg",
        "points": 52,
        "title": "Velocity Eau de Parfum - 50 ml",
        "price": 95,
        "status": "Linha Regular",
        "description": "Uma combinação de notas de flores e frutas exóticas.",
        "gridList": [
            {
                "SKU": "10-168700"
            }
        ]
    },
    {
        "id": 147,
        "session": "SPA e Fragrâncias",
        "line": "Perfumes",
        "image": "10-020031.jpg",
        "points": 32,
        "title": "Exotic Passionfruit Água de Colônia - 50 ml",
        "price": 63,
        "status": "Linha Regular",
        "description": "Doce e marcante.",
        "gridList": [
            {
                "SKU": "10-020031"
            }
        ]
    },
    {
        "id": 148,
        "session": "SPA e Fragrâncias",
        "line": "Perfumes",
        "image": "10-033691.jpg",
        "points": 32,
        "title": "Forever Orchid Água de Colônia - 50 ml",
        "price": 63,
        "status": "Linha Regular",
        "description": "Simples e ao mesmo tempo sofisticada.",
        "gridList": [
            {
                "SKU": "10-033691"
            }
        ]
    },
    {
        "id": 149,
        "session": "SPA e Fragrâncias",
        "line": "Perfumes",
        "image": "10-020029.jpg",
        "points": 32,
        "title": "Simply Cotton Água de Colônia - 50 ml",
        "price": 63,
        "status": "Linha Regular",
        "description": "Pura e refrescante.",
        "gridList": [
            {
                "SKU": "10-020029"
            }
        ]
    },
    {
        "id": 150,
        "session": "SPA e Fragrâncias",
        "line": "Perfumes",
        "image": "10-020028.jpg",
        "points": 32,
        "title": "Warm Amber Água de Colônia - 50 ml",
        "price": 63,
        "status": "Linha Regular",
        "description": "Rica e acolhedora.",
        "gridList": [
            {
                "SKU": "10-020028"
            }
        ]
    },
    {
        "id": 151,
        "session": "SPA e Fragrâncias",
        "line": "Perfumes",
        "image": "10-048515.jpg",
        "points": 60,
        "title": "True Original Cologne Spray - 59 ml",
        "price": 115,
        "status": "Linha Regular",
        "description": "Fragrância fougère aromática. Fresca, contemporânea e espontânea para o verdadeiro homem original.",
        "gridList": [
            {
                "SKU": "10-048515"
            }
        ]
    },
    {
        "id": 152,
        "session": "SPA e Fragrâncias",
        "line": "Perfumes",
        "image": "10-012494.jpg",
        "points": 60,
        "title": "MK High Intensity Cologne Spray - 73 ml",
        "price": 115,
        "status": "Linha Regular",
        "description": "Fragrância oriental âmbar com notas de topo de erva-doce negra e sálvia prata.",
        "gridList": [
            {
                "SKU": "10-012494"
            }
        ]
    },
    {
        "id": 153,
        "session": "SPA e Fragrâncias",
        "line": "Perfumes",
        "image": "10-028783.jpg",
        "points": 45,
        "title": "Domain Cologne - 73 ml",
        "price": 85,
        "status": "Linha Regular",
        "description": "Uma refrescante combinação de lavanda, musgo de carvalho e almíscar.",
        "gridList": [
            {
                "SKU": "10-028783"
            }
        ]
    },
    {
        "id": 154,
        "session": "SPA e Fragrâncias",
        "line": "Perfumes",
        "image": "10-501700.jpg",
        "points": 52,
        "title": "Velocity For Him - 59 ml",
        "price": 95,
        "status": "Linha Regular",
        "description": "Esta leve fragrância captura o frescor dos ares das montanhas e a essência de madeiras.",
        "gridList": [
            {
                "SKU": "10-501700"
            }
        ]
    },
    {
        "id": 155,
        "session": "Maquiagem",
        "line": "Maquiagem",
        "image": "02-237051.jpg",
        "points": 16,
        "title": "Brilho Labial Duo Mix",
        "price": 28,
        "status": "Promoção",
        "gridList": [
            {
                "SKU": "02-236951",
                "option": "Warm Coral"
            },
            {
                "SKU": "02-237251",
                "option": "Pink Pearl"
            },
            {
                "SKU": "02-237051",
                "option": "Redwood"
            }
        ]
    },
    {
        "id": 156,
        "session": "Maquiagem",
        "line": "Esmalte",
        "image": "02-237451.jpg",
        "points": 9,
        "title": "Esmalte para as Unhas",
        "price": 16,
        "status": "Promoção",
        "gridList": [
            {
                "SKU": "02-237551",
                "option": "Lava"
            },
            {
                "SKU": "02-237451",
                "option": "Crushed Pearl"
            }
        ]
    }
]